MANIFEST.in
README.md
setup.py
ConceptNet.egg-info/PKG-INFO
ConceptNet.egg-info/SOURCES.txt
ConceptNet.egg-info/dependency_links.txt
ConceptNet.egg-info/entry_points.txt
ConceptNet.egg-info/requires.txt
ConceptNet.egg-info/top_level.txt
conceptnet5/__init__.py
conceptnet5/api.py
conceptnet5/edges.py
conceptnet5/languages.py
conceptnet5/nodes.py
conceptnet5/relations.py
conceptnet5/uri.py
conceptnet5/builders/__init__.py
conceptnet5/builders/cli.py
conceptnet5/builders/combine_assertions.py
conceptnet5/builders/morphology.py
conceptnet5/builders/reduce_assoc.py
conceptnet5/db/__init__.py
conceptnet5/db/cli.py
conceptnet5/db/config.py
conceptnet5/db/connection.py
conceptnet5/db/prepare_data.py
conceptnet5/db/query.py
conceptnet5/db/schema.py
conceptnet5/formats/__init__.py
conceptnet5/formats/convert.py
conceptnet5/formats/json_stream.py
conceptnet5/formats/msgpack_stream.py
conceptnet5/formats/semantic_web.py
conceptnet5/language/__init__.py
conceptnet5/language/english.py
conceptnet5/language/lemmatize.py
conceptnet5/language/token_utils.py
conceptnet5/readers/__init__.py
conceptnet5/readers/cc_cedict.py
conceptnet5/readers/cli.py
conceptnet5/readers/conceptnet4.py
conceptnet5/readers/dbpedia.py
conceptnet5/readers/emoji.py
conceptnet5/readers/jmdict.py
conceptnet5/readers/kyoto_yahoo.py
conceptnet5/readers/nadya.py
conceptnet5/readers/opencyc.py
conceptnet5/readers/ptt_petgame.py
conceptnet5/readers/verbosity.py
conceptnet5/readers/wiktionary.py
conceptnet5/readers/wordnet.py
conceptnet5/support_data/README.txt
conceptnet5/support_data/afinn-adjusted.txt
conceptnet5/support_data/blacklist.txt
conceptnet5/support_data/cmudict-0.7b
conceptnet5/support_data/cmudict.0.7a
conceptnet5/support_data/demonym_article.txt
conceptnet5/support_data/myz_naacl13_test_set.tgz
conceptnet5/support_data/reliability.csv
conceptnet5/support_data/wordvectors-org-vocab.txt
conceptnet5/support_data/zh_frames.json
conceptnet5/support_data/bats/D1.txt
conceptnet5/support_data/bats/D10.txt
conceptnet5/support_data/bats/D2.txt
conceptnet5/support_data/bats/D3.txt
conceptnet5/support_data/bats/D4.txt
conceptnet5/support_data/bats/D5.txt
conceptnet5/support_data/bats/D6.txt
