Metadata-Version: 2.1
Name: ConceptNet
Version: 5.7.0
Summary: A semantic network of general knowledge
Home-page: UNKNOWN
Author: Robyn Speer
Author-email: rspeer@luminoso.com
License: Apache License 2.0
Platform: UNKNOWN
Requires-Python: >=3.5
Provides-Extra: vectors
